parsagon/__init__.py
parsagon/api.py
parsagon/assistant.py
parsagon/create.py
parsagon/custom_function.py
parsagon/edit.py
parsagon/exceptions.py
parsagon/executor.py
parsagon/gui_entry.py
parsagon/highlights.js
parsagon/main.py
parsagon/print.py
parsagon/runs.py
parsagon/secrets.py
parsagon/settings.py
parsagon/gui/__init__.py
parsagon/gui/controller.py
parsagon/gui/menu.py
parsagon/gui/window.py
parsagon/tests/__init__.py
parsagon/tests/api_mocks.py
parsagon/tests/conftest.py
parsagon/tests/test_executor.py
parsagon/tests/test_invalid_args.py
parsagon/tests/test_pipeline_operations.py
parsagon/tests/test_print.py
parsagon/tests/test_secrets.py
parsagon-0.17.2.dist-info/METADATA
parsagon-0.17.2.dist-info/WHEEL
parsagon-0.17.2.dist-info/entry_points.txt
parsagon-0.17.2.dist-info/top_level.txt
parsagon-0.17.2.dist-info/RECORD
