Metadata-Version: 2.4
Name: parsagon
Version: 0.17.2
Summary: Allows you to create browser automations with natural language
Author-email: Sandy Suh <sandy@parsagon.io>
Project-URL: Homepage, https://parsagon.io
Classifier: Programming Language :: Python :: 3
Classifier: Operating System :: OS Independent
Requires-Python: >=3.8
Requires-Dist: selenium==4.9.1
Requires-Dist: lxml[html_clean]==5.3.2
Requires-Dist: httpx>=0.27.0
Requires-Dist: psutil==7.0.0
Requires-Dist: rich==13.6.0
Requires-Dist: PyVirtualDisplay==3.0
Requires-Dist: selenium-wire==5.1.0
Requires-Dist: cssselect==1.2.0
Requires-Dist: undetected-chromedriver==3.5.5
Requires-Dist: webdriver-manager==4.0.2
Requires-Dist: jsonpath-ng==1.5.3
Requires-Dist: simplejson==3.19.1
Requires-Dist: PyMuPDF==1.26.4
Requires-Dist: pymupdf4llm==0.0.27
Requires-Dist: pypdf==5.9.0
Requires-Dist: python-dateutil==2.9.0.post0
Requires-Dist: html2text==2024.2.26
Requires-Dist: feedparser==6.0.11
Provides-Extra: dev
Requires-Dist: pytest==7.3.2; extra == "dev"
Requires-Dist: pytest-mock==3.11.1; extra == "dev"
Requires-Dist: pre-commit==3.6.0; extra == "dev"
